{
  "marketing_stripe": {
    "text": "FRETE PROMOCIONAL LIBERADO",
    "link": "",
    "color": "#090909"
  },
  "contacts_stripe": {
    "pages": [],
    "phone_wpp": true,
    "socials": true
  },
  "categories_list": {
    "featured": [
      "/sache-perfumado-via-aroma?QUEIMA DE ESTOQUE",
      "/maquinas-profissionais-para-aromatizacao-de-ambiente?MÁQUINAS PROFISSIONAIS & REFIS",
      "/refil-para-difusor-de-varetas?REFIL PARA DIFUSOR DE VARETAS"
    ],
    "random": 14,
    "full_width": true
  },
  "desktop_megamenu": true,
  "search_input": true,
  "alphabetical_order_submenu": true,
  "full_width_submenu": true
}